Metadata-Version: 1.0
Name: ecs-ansible-env
Version: 0.0.1.2
Summary: Package used to mimic env files in docker compose
Home-page: https://github.com/mwaaas/ecs_ansible_env_file
Author: mwaaas
Author-email: francismwangi152@gmail.com
License: UNKNOWN
Platform: UNKNOWN
